LICENSE.txt
MANIFEST.in
README.rst
setup.py
config/default.cfg
docs/Makefile
docs/ROyWeb_Screenshot.png
docs/api.rst
docs/conf.py
docs/index.rst
docs/install.rst
docs/usage.rst
royweb/__init__.py
royweb/__main__.py
royweb/__version__.py
royweb/database.py
royweb/networking.py
royweb/session.py
royweb/webhandler.py
royweb.egg-info/PKG-INFO
royweb.egg-info/SOURCES.txt
royweb.egg-info/dependency_links.txt
royweb.egg-info/entry_points.txt
royweb.egg-info/requires.txt
royweb.egg-info/top_level.txt
royweb/static/css/bootstrap-theme.css
royweb/static/css/bootstrap-theme.css.map
royweb/static/css/bootstrap-theme.min.css
royweb/static/css/bootstrap.css
royweb/static/css/bootstrap.css.map
royweb/static/css/bootstrap.min.css
royweb/static/css/c3.min.css
royweb/static/css/graphs.css
royweb/static/css/main.css
royweb/static/css/menu.css
royweb/static/css/sidebar.css
royweb/static/css/v2.css
royweb/static/css/smoothness/jquery-ui-1.10.4.custom.css
royweb/static/css/smoothness/jquery-ui-1.10.4.custom.min.css
royweb/static/css/smoothness/images/animated-overlay.gif
royweb/static/css/smoothness/images/ui-bg_flat_0_aaaaaa_40x100.png
royweb/static/css/smoothness/images/ui-bg_flat_75_ffffff_40x100.png
royweb/static/css/smoothness/images/ui-bg_glass_55_fbf9ee_1x400.png
royweb/static/css/smoothness/images/ui-bg_glass_65_ffffff_1x400.png
royweb/static/css/smoothness/images/ui-bg_glass_75_dadada_1x400.png
royweb/static/css/smoothness/images/ui-bg_glass_75_e6e6e6_1x400.png
royweb/static/css/smoothness/images/ui-bg_glass_95_fef1ec_1x400.png
royweb/static/css/smoothness/images/ui-bg_highlight-soft_75_cccccc_1x100.png
royweb/static/css/smoothness/images/ui-icons_222222_256x240.png
royweb/static/css/smoothness/images/ui-icons_2e83ff_256x240.png
royweb/static/css/smoothness/images/ui-icons_454545_256x240.png
royweb/static/css/smoothness/images/ui-icons_888888_256x240.png
royweb/static/css/smoothness/images/ui-icons_cd0a0a_256x240.png
royweb/static/fonts/glyphicons-halflings-regular.eot
royweb/static/fonts/glyphicons-halflings-regular.svg
royweb/static/fonts/glyphicons-halflings-regular.ttf
royweb/static/fonts/glyphicons-halflings-regular.woff
