Metadata-Version: 1.1
Name: royweb
Version: 0.9.5
Summary: Restless Oyster online monitoring tool
Home-page: http://github.com/tamasgal/royweb/
Author: Tamas Gal
Author-email: tgal@km3net.de
License: UNKNOWN
Platform: any
Classifier: Development Status :: 3 - Alpha
Classifier: Intended Audience :: Developers
Classifier: Intended Audience :: Science/Research
Classifier: Intended Audience :: System Administrators
Classifier: Programming Language :: Python
Classifier: Programming Language :: JavaScript
Classifier: Topic :: Scientific/Engineering :: Visualization
Classifier: Topic :: Internet :: WWW/HTTP :: Dynamic Content
Classifier: Topic :: Internet :: WWW/HTTP :: HTTP Servers
Classifier: Environment :: Web Environment
